{"textures":{"2":"modelengine:entity/pillars"},"elements":[{"from":[7.3642855,7.0899057,6.4214287],"to":[8.65,8.777406,7.707143],"rotation":{"angle":0.0,"axis":"y","origin":[8.007143,7.732763,7.0642858]},"faces":{"east":{"uv":[8.75,13.125,8.890625,13.308594],"rotation":0,"texture":"#2","tintindex":0},"south":{"uv":[8.9375,13.125,9.078125,13.308594],"rotation":0,"texture":"#2","tintindex":0},"north":{"uv":[8.5625,13.125,8.703125,13.308594],"rotation":0,"texture":"#2","tintindex":0},"west":{"uv":[9.8125,13.125,9.953125,13.308594],"rotation":0,"texture":"#2","tintindex":0},"up":{"uv":[4.078125,13.640625,3.9375,13.5],"rotation":0,"texture":"#2","tintindex":0},"down":{"uv":[13.640625,3.9375,13.5,4.078125],"rotation":0,"texture":"#2","tintindex":0}}},{"from":[7.1232142,7.0899057,6.582143],"to":[7.3642855,8.134548,7.5464287],"rotation":{"angle":0.0,"axis":"y","origin":[7.2839284,7.612227,7.0642858]},"faces":{"east":{"uv":[13.875,9.6875,13.980469,9.800781],"rotation":0,"texture":"#2","tintindex":0},"south":{"uv":[7.875,14.75,7.9023438,14.863281],"rotation":0,"texture":"#2","tintindex":0},"north":{"uv":[7.8125,14.75,7.8398438,14.863281],"rotation":0,"texture":"#2","tintindex":0},"west":{"uv":[13.875,9.8125,13.980469,9.925781],"rotation":0,"texture":"#2","tintindex":0},"up":{"uv":[14.777344,12.167969,14.75,12.0625],"rotation":0,"texture":"#2","tintindex":0},"down":{"uv":[12.152344,14.75,12.125,14.855469],"rotation":0,"texture":"#2","tintindex":0}}},{"from":[7.1232142,8.134548,6.823214],"to":[7.3642855,8.777406,7.305357],"rotation":{"angle":0.0,"axis":"y","origin":[7.2839284,8.455977,7.0642858]},"faces":{"east":{"uv":[11.125,14.625,11.1796875,14.6953125],"rotation":0,"texture":"#2","tintindex":0},"south":{"uv":[14.875,7.75,14.902344,7.8203125],"rotation":0,"texture":"#2","tintindex":0},"north":{"uv":[7.75,14.875,7.7773438,14.9453125],"rotation":0,"texture":"#2","tintindex":0},"west":{"uv":[11.1875,14.625,11.2421875,14.6953125],"rotation":0,"texture":"#2","tintindex":0},"up":{"uv":[2.0898438,15.0546875,2.0625,15.0],"rotation":0,"texture":"#2","tintindex":0},"down":{"uv":[15.027344,2.0625,15.0,2.1171875],"rotation":0,"texture":"#2","tintindex":0}}},{"from":[8.65,7.0899057,6.742857],"to":[8.810715,8.134548,7.385714],"rotation":{"angle":0.0,"axis":"y","origin":[8.730357,7.612227,7.0642858]},"faces":{"east":{"uv":[14.125,9.9375,14.1953125,10.050781],"rotation":0,"texture":"#2","tintindex":0},"south":{"uv":[6.1875,14.8125,6.2070312,14.925781],"rotation":0,"texture":"#2","tintindex":0},"north":{"uv":[14.8125,6.125,14.832031,6.2382812],"rotation":0,"texture":"#2","tintindex":0},"west":{"uv":[14.125,10.125,14.1953125,10.238281],"rotation":0,"texture":"#2","tintindex":0},"up":{"uv":[6.8945312,15.0703125,6.875,15.0],"rotation":0,"texture":"#2","tintindex":0},"down":{"uv":[6.9570312,15.0,6.9375,15.0703125],"rotation":0,"texture":"#2","tintindex":0}}},{"from":[8.65,8.134548,6.903571],"to":[8.810715,8.777406,7.225],"rotation":{"angle":0.0,"axis":"y","origin":[8.730357,8.455977,7.0642858]},"faces":{"east":{"uv":[14.8125,4.125,14.847656,4.1953125],"rotation":0,"texture":"#2","tintindex":0},"south":{"uv":[15.0,7.0,15.019531,7.0703125],"rotation":0,"texture":"#2","tintindex":0},"north":{"uv":[7.0,15.0,7.0195312,15.0703125],"rotation":0,"texture":"#2","tintindex":0},"west":{"uv":[4.1875,14.8125,4.2226562,14.8828125],"rotation":0,"texture":"#2","tintindex":0},"up":{"uv":[15.144531,14.972656,15.125,14.9375],"rotation":0,"texture":"#2","tintindex":0},"down":{"uv":[15.019531,15.125,15.0,15.160156],"rotation":0,"texture":"#2","tintindex":0}}},{"from":[7.525,7.0899057,6.180357],"to":[8.489285,8.134548,6.4214287],"rotation":{"angle":0.0,"axis":"y","origin":[8.007143,7.732763,6.823214]},"faces":{"east":{"uv":[14.75,7.875,14.777344,7.9882812],"rotation":0,"texture":"#2","tintindex":0},"south":{"uv":[13.875,10.0625,13.980469,10.175781],"rotation":0,"texture":"#2","tintindex":0},"north":{"uv":[13.875,9.9375,13.980469,10.050781],"rotation":0,"texture":"#2","tintindex":0},"west":{"uv":[7.9375,14.75,7.9648438,14.863281],"rotation":0,"texture":"#2","tintindex":0},"up":{"uv":[12.292969,14.777344,12.1875,14.75],"rotation":0,"texture":"#2","tintindex":0},"down":{"uv":[14.855469,12.1875,14.75,12.214844],"rotation":0,"texture":"#2","tintindex":0}}},{"from":[7.774107,8.134548,6.180357],"to":[8.25625,8.777406,6.4214287],"rotation":{"angle":0.0,"axis":"y","origin":[8.055357,8.455977,6.300893]},"faces":{"east":{"uv":[7.8125,14.875,7.8398438,14.9453125],"rotation":0,"texture":"#2","tintindex":0},"south":{"uv":[11.3125,14.625,11.3671875,14.6953125],"rotation":0,"texture":"#2","tintindex":0},"north":{"uv":[11.25,14.625,11.3046875,14.6953125],"rotation":0,"texture":"#2","tintindex":0},"west":{"uv":[7.875,14.875,7.9023438,14.9453125],"rotation":0,"texture":"#2","tintindex":0},"up":{"uv":[2.1796875,15.027344,2.125,15.0],"rotation":0,"texture":"#2","tintindex":0},"down":{"uv":[15.0546875,2.125,15.0,2.1523438],"rotation":0,"texture":"#2","tintindex":0}}},{"from":[7.774107,8.134548,7.707143],"to":[8.25625,8.777406,7.948214],"rotation":{"angle":0.0,"axis":"y","origin":[8.055357,8.455977,7.8276787]},"faces":{"east":{"uv":[14.875,7.875,14.902344,7.9453125],"rotation":0,"texture":"#2","tintindex":0},"south":{"uv":[11.4375,14.625,11.4921875,14.6953125],"rotation":0,"texture":"#2","tintindex":0},"north":{"uv":[14.625,11.3125,14.6796875,11.3828125],"rotation":0,"texture":"#2","tintindex":0},"west":{"uv":[7.9375,14.875,7.9648438,14.9453125],"rotation":0,"texture":"#2","tintindex":0},"up":{"uv":[2.2421875,15.027344,2.1875,15.0],"rotation":0,"texture":"#2","tintindex":0},"down":{"uv":[15.0546875,2.1875,15.0,2.2148438],"rotation":0,"texture":"#2","tintindex":0}}},{"from":[7.525,7.0899057,7.707143],"to":[8.489285,8.134548,7.948214],"rotation":{"angle":0.0,"axis":"y","origin":[8.007143,7.732763,8.35]},"faces":{"east":{"uv":[8.0,14.75,8.027344,14.863281],"rotation":0,"texture":"#2","tintindex":0},"south":{"uv":[13.875,10.3125,13.980469,10.425781],"rotation":0,"texture":"#2","tintindex":0},"north":{"uv":[13.875,10.1875,13.980469,10.300781],"rotation":0,"texture":"#2","tintindex":0},"west":{"uv":[14.75,8.0,14.777344,8.113281],"rotation":0,"texture":"#2","tintindex":0},"up":{"uv":[14.855469,12.277344,14.75,12.25],"rotation":0,"texture":"#2","tintindex":0},"down":{"uv":[12.417969,14.75,12.3125,14.777344],"rotation":0,"texture":"#2","tintindex":0}}}],"display":{"head":{"translation":[0.0,-6.4,0.0],"scale":[4.0,4.0,4.0]}}}