{"textures":{"0":"sunrise:races/shark_backfin"},"elements":[{"from":[7.9,13.22172,13.398653],"to":[8.1,13.871719,16.148653],"faces":{"east":{"uv":[4.5,1.5,5.875,1.75],"tintindex":0,"rotation":0,"texture":"#0"},"south":{"uv":[7.5,5.0,7.625,5.25],"tintindex":0,"rotation":0,"texture":"#0"},"north":{"uv":[7.5,4.5,7.625,4.75],"tintindex":0,"rotation":0,"texture":"#0"},"west":{"uv":[4.5,2.0,5.875,2.25],"tintindex":0,"rotation":0,"texture":"#0"},"up":{"uv":[6.625,7.875,6.5,6.5],"tintindex":0,"rotation":0,"texture":"#0"},"down":{"uv":[7.125,0.5,7.0,1.875],"tintindex":0,"rotation":0,"texture":"#0"}},"rotation":{"origin":[8.0,13.5467205,14.773653],"angle":45.0,"axis":"x"}},{"from":[7.9,5.849661,10.071396],"to":[8.1,11.849661,15.071396],"faces":{"east":{"uv":[0.0,0.0,2.5,2.25],"tintindex":0,"rotation":0,"texture":"#0"},"south":{"uv":[2.0,5.0,2.125,7.25],"tintindex":0,"rotation":0,"texture":"#0"},"north":{"uv":[1.5,5.0,1.625,7.25],"tintindex":0,"rotation":0,"texture":"#0"},"west":{"uv":[0.0,2.5,2.5,4.75],"tintindex":0,"rotation":0,"texture":"#0"},"up":{"uv":[0.625,7.5,0.5,5.0],"tintindex":0,"rotation":0,"texture":"#0"},"down":{"uv":[1.125,5.0,1.0,7.5],"tintindex":0,"rotation":0,"texture":"#0"}}},{"from":[7.9,13.9995365,14.67647],"to":[8.1,14.649538,16.42647],"faces":{"east":{"uv":[4.5,3.5,5.375,3.75],"tintindex":0,"rotation":0,"texture":"#0"},"south":{"uv":[7.0,7.5,7.125,7.75],"tintindex":0,"rotation":0,"texture":"#0"},"north":{"uv":[7.5,6.5,7.625,6.75],"tintindex":0,"rotation":0,"texture":"#0"},"west":{"uv":[5.5,3.5,6.375,3.75],"tintindex":0,"rotation":0,"texture":"#0"},"up":{"uv":[6.125,3.375,6.0,2.5],"tintindex":0,"rotation":0,"texture":"#0"},"down":{"uv":[7.125,5.5,7.0,6.375],"tintindex":0,"rotation":0,"texture":"#0"}},"rotation":{"origin":[8.0,14.324537,15.55147],"angle":45.0,"axis":"x"}},{"from":[7.9,14.777355,15.954288],"to":[8.1,15.427355,16.704288],"faces":{"east":{"uv":[7.5,0.0,7.875,0.25],"tintindex":0,"rotation":0,"texture":"#0"},"south":{"uv":[8.0,0.0,8.125,0.25],"tintindex":0,"rotation":0,"texture":"#0"},"north":{"uv":[0.0,8.0,0.125,8.25],"tintindex":0,"rotation":0,"texture":"#0"},"west":{"uv":[0.5,7.5,0.875,7.75],"tintindex":0,"rotation":0,"texture":"#0"},"up":{"uv":[1.625,7.875,1.5,7.5],"tintindex":0,"rotation":0,"texture":"#0"},"down":{"uv":[7.625,1.5,7.5,1.875],"tintindex":0,"rotation":0,"texture":"#0"}},"rotation":{"origin":[8.0,15.102354,16.329288],"angle":45.0,"axis":"x"}},{"from":[7.9,11.176744,11.345962],"to":[8.1,14.926744,11.695961],"faces":{"east":{"uv":[6.5,2.5,6.625,4.375],"tintindex":0,"rotation":0,"texture":"#0"},"south":{"uv":[6.5,4.5,6.625,6.375],"tintindex":0,"rotation":0,"texture":"#0"},"north":{"uv":[6.5,0.5,6.625,2.375],"tintindex":0,"rotation":0,"texture":"#0"},"west":{"uv":[5.0,6.5,5.125,8.375],"tintindex":0,"rotation":0,"texture":"#0"},"up":{"uv":[0.625,8.125,0.5,8.0],"tintindex":0,"rotation":0,"texture":"#0"},"down":{"uv":[8.125,0.5,8.0,0.625],"tintindex":0,"rotation":0,"texture":"#0"}},"rotation":{"origin":[8.0,13.051744,11.520962],"angle":45.0,"axis":"x"}},{"from":[7.9,9.797886,11.02482],"to":[8.1,13.547886,14.774819],"faces":{"east":{"uv":[2.5,0.0,4.375,1.875],"tintindex":0,"rotation":0,"texture":"#0"},"south":{"uv":[5.5,4.5,5.625,6.375],"tintindex":0,"rotation":0,"texture":"#0"},"north":{"uv":[5.0,4.5,5.125,6.375],"tintindex":0,"rotation":0,"texture":"#0"},"west":{"uv":[2.5,2.0,4.375,3.875],"tintindex":0,"rotation":0,"texture":"#0"},"up":{"uv":[6.125,2.375,6.0,0.5],"tintindex":0,"rotation":0,"texture":"#0"},"down":{"uv":[6.125,4.5,6.0,6.375],"tintindex":0,"rotation":0,"texture":"#0"}},"rotation":{"origin":[8.0,11.672886,12.899819],"angle":45.0,"axis":"x"}},{"from":[7.9,14.388445,15.315379],"to":[8.1,15.038446,16.56538],"faces":{"east":{"uv":[7.0,2.0,7.625,2.25],"tintindex":0,"rotation":0,"texture":"#0"},"south":{"uv":[7.5,7.5,7.625,7.75],"tintindex":0,"rotation":0,"texture":"#0"},"north":{"uv":[7.5,7.0,7.625,7.25],"tintindex":0,"rotation":0,"texture":"#0"},"west":{"uv":[2.5,7.0,3.125,7.25],"tintindex":0,"rotation":0,"texture":"#0"},"up":{"uv":[7.625,1.125,7.5,0.5],"tintindex":0,"rotation":0,"texture":"#0"},"down":{"uv":[1.125,7.5,1.0,8.125],"tintindex":0,"rotation":0,"texture":"#0"}},"rotation":{"origin":[8.0,14.713446,15.940379],"angle":45.0,"axis":"x"}},{"from":[7.9,12.9212,12.796356],"to":[8.1,13.571199,15.796356],"faces":{"east":{"uv":[4.5,0.5,6.0,0.75],"tintindex":0,"rotation":0,"texture":"#0"},"south":{"uv":[4.5,7.5,4.625,7.75],"tintindex":0,"rotation":0,"texture":"#0"},"north":{"uv":[7.5,4.0,7.625,4.25],"tintindex":0,"rotation":0,"texture":"#0"},"west":{"uv":[4.5,1.0,6.0,1.25],"tintindex":0,"rotation":0,"texture":"#0"},"up":{"uv":[5.625,8.0,5.5,6.5],"tintindex":0,"rotation":0,"texture":"#0"},"down":{"uv":[6.125,6.5,6.0,8.0],"tintindex":0,"rotation":0,"texture":"#0"}},"rotation":{"origin":[8.0,13.246199,14.296356],"angle":45.0,"axis":"x"}},{"from":[7.9,10.217644,15.528186],"to":[8.1,16.017643,16.128185],"faces":{"east":{"uv":[2.5,4.0,2.8125,6.875],"tintindex":0,"rotation":0,"texture":"#0"},"south":{"uv":[4.0,4.5,4.125,7.375],"tintindex":0,"rotation":0,"texture":"#0"},"north":{"uv":[3.5,4.5,3.625,7.375],"tintindex":0,"rotation":0,"texture":"#0"},"west":{"uv":[3.0,4.0,3.3125,6.875],"tintindex":0,"rotation":0,"texture":"#0"},"up":{"uv":[7.625,2.8125,7.5,2.5],"tintindex":0,"rotation":0,"texture":"#0"},"down":{"uv":[3.125,7.5,3.0,7.8125],"tintindex":0,"rotation":0,"texture":"#0"}},"rotation":{"origin":[8.0,13.117643,15.828186],"angle":22.5,"axis":"x"}},{"from":[7.9,15.400881,16.565056],"to":[8.1,16.000881,17.215057],"faces":{"east":{"uv":[7.0,6.5,7.3125,6.8125],"tintindex":0,"rotation":0,"texture":"#0"},"south":{"uv":[3.5,7.5,3.625,7.8125],"tintindex":0,"rotation":0,"texture":"#0"},"north":{"uv":[7.5,3.0,7.625,3.3125],"tintindex":0,"rotation":0,"texture":"#0"},"west":{"uv":[7.0,7.0,7.3125,7.3125],"tintindex":0,"rotation":0,"texture":"#0"},"up":{"uv":[7.625,3.8125,7.5,3.5],"tintindex":0,"rotation":0,"texture":"#0"},"down":{"uv":[4.125,7.5,4.0,7.8125],"tintindex":0,"rotation":0,"texture":"#0"}}},{"from":[7.9,14.438311,12.060873],"to":[8.1,15.038309,17.210873],"faces":{"east":{"uv":[3.5,4.0,6.0625,4.3125],"tintindex":0,"rotation":0,"texture":"#0"},"south":{"uv":[2.5,7.5,2.625,7.8125],"tintindex":0,"rotation":0,"texture":"#0"},"north":{"uv":[2.0,7.5,2.125,7.8125],"tintindex":0,"rotation":0,"texture":"#0"},"west":{"uv":[4.5,0.0,7.0625,0.3125],"tintindex":0,"rotation":0,"texture":"#0"},"up":{"uv":[4.625,7.0625,4.5,4.5],"tintindex":0,"rotation":0,"texture":"#0"},"down":{"uv":[0.125,5.0,0.0,7.5625],"tintindex":0,"rotation":0,"texture":"#0"}},"rotation":{"origin":[8.0,14.73831,14.635873],"angle":-22.5,"axis":"x"}},{"from":[7.9,13.610628,14.037561],"to":[8.1,14.260628,16.287561],"faces":{"east":{"uv":[4.5,2.5,5.625,2.75],"tintindex":0,"rotation":0,"texture":"#0"},"south":{"uv":[7.5,6.0,7.625,6.25],"tintindex":0,"rotation":0,"texture":"#0"},"north":{"uv":[7.5,5.5,7.625,5.75],"tintindex":0,"rotation":0,"texture":"#0"},"west":{"uv":[4.5,3.0,5.625,3.25],"tintindex":0,"rotation":0,"texture":"#0"},"up":{"uv":[7.125,3.625,7.0,2.5],"tintindex":0,"rotation":0,"texture":"#0"},"down":{"uv":[7.125,4.0,7.0,5.125],"tintindex":0,"rotation":0,"texture":"#0"}},"rotation":{"origin":[8.0,13.935629,15.162561],"angle":45.0,"axis":"x"}}]}