{"textures":{"2":"modelengine:entity/pillars"},"elements":[{"from":[7.376562,6.740538,7.20625],"to":[8.642187,8.111631,7.5226564],"faces":{"east":{"uv":[14.875,10.625,14.894531,10.7109375],"tintindex":0,"rotation":0,"texture":"#2"},"south":{"uv":[14.1875,11.6875,14.265625,11.7734375],"tintindex":0,"rotation":0,"texture":"#2"},"north":{"uv":[11.6875,14.1875,11.765625,14.2734375],"tintindex":0,"rotation":0,"texture":"#2"},"west":{"uv":[14.875,10.75,14.894531,10.8359375],"tintindex":0,"rotation":0,"texture":"#2"},"up":{"uv":[6.015625,14.957031,5.9375,14.9375],"tintindex":0,"rotation":0,"texture":"#2"},"down":{"uv":[15.015625,5.9375,14.9375,5.9570312],"tintindex":0,"rotation":0,"texture":"#2"}}},{"from":[7.376562,6.740538,5.202344],"to":[8.642187,8.111631,5.51875],"faces":{"east":{"uv":[14.875,10.375,14.894531,10.4609375],"tintindex":0,"rotation":0,"texture":"#2"},"south":{"uv":[14.1875,11.5625,14.265625,11.6484375],"tintindex":0,"rotation":0,"texture":"#2"},"north":{"uv":[11.5625,14.1875,11.640625,14.2734375],"tintindex":0,"rotation":0,"texture":"#2"},"west":{"uv":[14.875,10.5,14.894531,10.5859375],"tintindex":0,"rotation":0,"texture":"#2"},"up":{"uv":[5.890625,14.957031,5.8125,14.9375],"tintindex":0,"rotation":0,"texture":"#2"},"down":{"uv":[15.015625,5.875,14.9375,5.8945312],"tintindex":0,"rotation":0,"texture":"#2"}}},{"from":[6.8492184,8.111631,6.046094],"to":[7.1656246,8.955381,6.6789064],"faces":{"east":{"uv":[14.8125,12.125,14.8515625,12.1796875],"tintindex":0,"rotation":0,"texture":"#2"},"south":{"uv":[15.0625,4.8125,15.082031,4.8671875],"tintindex":0,"rotation":0,"texture":"#2"},"north":{"uv":[4.8125,15.0625,4.8320312,15.1171875],"tintindex":0,"rotation":0,"texture":"#2"},"west":{"uv":[12.1875,14.8125,12.2265625,14.8671875],"tintindex":0,"rotation":0,"texture":"#2"},"up":{"uv":[15.144531,11.6640625,15.125,11.625],"tintindex":0,"rotation":0,"texture":"#2"},"down":{"uv":[11.707031,15.125,11.6875,15.1640625],"tintindex":0,"rotation":0,"texture":"#2"}}},{"from":[7.1656246,6.740538,5.51875],"to":[8.853125,8.955381,7.20625],"faces":{"east":{"uv":[3.25,13.6875,3.3554688,13.824219],"tintindex":0,"rotation":0,"texture":"#2"},"south":{"uv":[13.6875,3.25,13.792969,3.3867188],"tintindex":0,"rotation":0,"texture":"#2"},"north":{"uv":[3.125,13.6875,3.2304688,13.824219],"tintindex":0,"rotation":0,"texture":"#2"},"west":{"uv":[3.375,13.6875,3.4804688,13.824219],"tintindex":0,"rotation":0,"texture":"#2"},"up":{"uv":[14.105469,11.667969,14.0,11.5625],"tintindex":0,"rotation":0,"texture":"#2"},"down":{"uv":[11.917969,14.0,11.8125,14.105469],"tintindex":0,"rotation":0,"texture":"#2"}}},{"from":[7.703516,8.111631,5.202344],"to":[8.3363285,8.955381,5.51875],"faces":{"east":{"uv":[15.0625,4.875,15.082031,4.9296875],"tintindex":0,"rotation":0,"texture":"#2"},"south":{"uv":[12.3125,14.8125,12.3515625,14.8671875],"tintindex":0,"rotation":0,"texture":"#2"},"north":{"uv":[12.25,14.8125,12.2890625,14.8671875],"tintindex":0,"rotation":0,"texture":"#2"},"west":{"uv":[15.0625,4.9375,15.082031,4.9921875],"tintindex":0,"rotation":0,"texture":"#2"},"up":{"uv":[15.1640625,11.707031,15.125,11.6875],"tintindex":0,"rotation":0,"texture":"#2"},"down":{"uv":[11.7890625,15.125,11.75,15.144531],"tintindex":0,"rotation":0,"texture":"#2"}}},{"from":[8.853125,8.111631,6.1515627],"to":[9.064062,8.955381,6.5734377],"faces":{"east":{"uv":[1.0,15.0,1.0273438,15.0546875],"tintindex":0,"rotation":0,"texture":"#2"},"south":{"uv":[9.6875,15.1875,9.699219,15.2421875],"tintindex":0,"rotation":0,"texture":"#2"},"north":{"uv":[15.1875,9.625,15.199219,9.6796875],"tintindex":0,"rotation":0,"texture":"#2"},"west":{"uv":[15.0,1.0,15.027344,1.0546875],"tintindex":0,"rotation":0,"texture":"#2"},"up":{"uv":[15.324219,8.089844,15.3125,8.0625],"tintindex":0,"rotation":0,"texture":"#2"},"down":{"uv":[8.136719,15.3125,8.125,15.339844],"tintindex":0,"rotation":0,"texture":"#2"}}},{"from":[7.703516,8.111631,7.20625],"to":[8.3363285,8.955381,7.5226564],"faces":{"east":{"uv":[15.0625,5.0,15.082031,5.0546875],"tintindex":0,"rotation":0,"texture":"#2"},"south":{"uv":[12.375,14.8125,12.4140625,14.8671875],"tintindex":0,"rotation":0,"texture":"#2"},"north":{"uv":[14.8125,12.3125,14.8515625,12.3671875],"tintindex":0,"rotation":0,"texture":"#2"},"west":{"uv":[15.0625,5.0625,15.082031,5.1171875],"tintindex":0,"rotation":0,"texture":"#2"},"up":{"uv":[15.1640625,11.769531,15.125,11.75],"tintindex":0,"rotation":0,"texture":"#2"},"down":{"uv":[11.8515625,15.125,11.8125,15.144531],"tintindex":0,"rotation":0,"texture":"#2"}}},{"from":[6.8492184,6.740538,5.7296877],"to":[7.1656246,8.111631,6.9953127],"faces":{"east":{"uv":[14.1875,11.3125,14.265625,11.3984375],"tintindex":0,"rotation":0,"texture":"#2"},"south":{"uv":[10.3125,14.875,10.332031,14.9609375],"tintindex":0,"rotation":0,"texture":"#2"},"north":{"uv":[14.875,10.25,14.894531,10.3359375],"tintindex":0,"rotation":0,"texture":"#2"},"west":{"uv":[14.1875,11.4375,14.265625,11.5234375],"tintindex":0,"rotation":0,"texture":"#2"},"up":{"uv":[5.7695312,15.015625,5.75,14.9375],"tintindex":0,"rotation":0,"texture":"#2"},"down":{"uv":[14.957031,5.75,14.9375,5.828125],"tintindex":0,"rotation":0,"texture":"#2"}}},{"from":[8.853125,6.740538,5.940625],"to":[9.064062,8.111631,6.784375],"faces":{"east":{"uv":[14.5625,5.5625,14.6171875,5.6484375],"tintindex":0,"rotation":0,"texture":"#2"},"south":{"uv":[7.25,15.0625,7.2617188,15.1484375],"tintindex":0,"rotation":0,"texture":"#2"},"north":{"uv":[7.1875,15.0625,7.1992188,15.1484375],"tintindex":0,"rotation":0,"texture":"#2"},"west":{"uv":[14.5625,5.6875,14.6171875,5.7734375],"tintindex":0,"rotation":0,"texture":"#2"},"up":{"uv":[15.199219,9.6171875,15.1875,9.5625],"tintindex":0,"rotation":0,"texture":"#2"},"down":{"uv":[9.636719,15.1875,9.625,15.2421875],"tintindex":0,"rotation":0,"texture":"#2"}}}]}