{"textures":{"0":"modelengine:entity/cluster"},"elements":[{"from":[10.5,-5.749998,-5.0],"to":[10.75,-4.999998,-2.75],"faces":{"east":{"uv":[12.25,11.375,12.5,11.5],"tintindex":0,"rotation":0,"texture":"#0"},"south":{"uv":[11.625,12.375,11.75,12.5],"tintindex":0,"rotation":0,"texture":"#0"},"north":{"uv":[11.5,12.375,11.625,12.5],"tintindex":0,"rotation":0,"texture":"#0"},"west":{"uv":[12.25,11.5,12.5,11.625],"tintindex":0,"rotation":0,"texture":"#0"},"up":{"uv":[11.5,12.5,11.375,12.25],"tintindex":0,"rotation":0,"texture":"#0"},"down":{"uv":[12.375,11.625,12.25,11.875],"tintindex":0,"rotation":0,"texture":"#0"}}},{"from":[5.25,-6.749998,-7.25],"to":[5.5,-4.999998,-5.0],"faces":{"east":{"uv":[12.0,2.0,12.25,2.25],"tintindex":0,"rotation":0,"texture":"#0"},"south":{"uv":[12.25,10.0,12.375,10.25],"tintindex":0,"rotation":0,"texture":"#0"},"north":{"uv":[12.25,9.75,12.375,10.0],"tintindex":0,"rotation":0,"texture":"#0"},"west":{"uv":[12.0,2.25,12.25,2.5],"tintindex":0,"rotation":0,"texture":"#0"},"up":{"uv":[10.5,12.5,10.375,12.25],"tintindex":0,"rotation":0,"texture":"#0"},"down":{"uv":[12.375,10.375,12.25,10.625],"tintindex":0,"rotation":0,"texture":"#0"}}},{"from":[10.5,-6.749998,-7.25],"to":[10.75,-4.999998,-5.0],"faces":{"east":{"uv":[2.5,12.0,2.75,12.25],"tintindex":0,"rotation":0,"texture":"#0"},"south":{"uv":[12.125,12.25,12.25,12.5],"tintindex":0,"rotation":0,"texture":"#0"},"north":{"uv":[12.25,11.875,12.375,12.125],"tintindex":0,"rotation":0,"texture":"#0"},"west":{"uv":[2.75,12.0,3.0,12.25],"tintindex":0,"rotation":0,"texture":"#0"},"up":{"uv":[12.375,12.375,12.25,12.125],"tintindex":0,"rotation":0,"texture":"#0"},"down":{"uv":[12.5,0.25,12.375,0.5],"tintindex":0,"rotation":0,"texture":"#0"}}},{"from":[5.25,-5.749998,-5.0],"to":[5.5,-4.999998,-2.75],"faces":{"east":{"uv":[12.25,10.625,12.5,10.75],"tintindex":0,"rotation":0,"texture":"#0"},"south":{"uv":[12.375,11.25,12.5,11.375],"tintindex":0,"rotation":0,"texture":"#0"},"north":{"uv":[11.25,12.375,11.375,12.5],"tintindex":0,"rotation":0,"texture":"#0"},"west":{"uv":[12.25,10.75,12.5,10.875],"tintindex":0,"rotation":0,"texture":"#0"},"up":{"uv":[12.375,11.125,12.25,10.875],"tintindex":0,"rotation":0,"texture":"#0"},"down":{"uv":[12.375,11.125,12.25,11.375],"tintindex":0,"rotation":0,"texture":"#0"}}},{"from":[5.5,-6.749998,-7.25],"to":[10.5,-4.999998,-7.0],"faces":{"east":{"uv":[12.375,0.625,12.5,0.875],"tintindex":0,"rotation":0,"texture":"#0"},"south":{"uv":[10.5,0.75,11.125,1.0],"tintindex":0,"rotation":0,"texture":"#0"},"north":{"uv":[10.5,0.5,11.125,0.75],"tintindex":0,"rotation":0,"texture":"#0"},"west":{"uv":[1.125,12.375,1.25,12.625],"tintindex":0,"rotation":0,"texture":"#0"},"up":{"uv":[12.5,2.75,11.875,2.625],"tintindex":0,"rotation":0,"texture":"#0"},"down":{"uv":[12.5,2.75,11.875,2.875],"tintindex":0,"rotation":0,"texture":"#0"}}},{"from":[5.5,-5.749998,-3.0],"to":[10.5,-4.999998,-2.75],"faces":{"east":{"uv":[12.375,11.625,12.5,11.75],"tintindex":0,"rotation":0,"texture":"#0"},"south":{"uv":[11.875,3.0,12.5,3.125],"tintindex":0,"rotation":0,"texture":"#0"},"north":{"uv":[11.875,2.875,12.5,3.0],"tintindex":0,"rotation":0,"texture":"#0"},"west":{"uv":[11.75,12.375,11.875,12.5],"tintindex":0,"rotation":0,"texture":"#0"},"up":{"uv":[12.5,3.25,11.875,3.125],"tintindex":0,"rotation":0,"texture":"#0"},"down":{"uv":[4.125,11.875,3.5,12.0],"tintindex":0,"rotation":0,"texture":"#0"}}}]}