{"textures":{"2":"modelengine:entity/pillars"},"elements":[{"from":[7.6821427,7.5908356,2.1249995],"to":[8.325,8.434586,2.767857],"rotation":{"angle":0.0,"axis":"y","origin":[8.0035715,7.9122643,2.4464283]},"faces":{"east":{"uv":[11.6875,14.3125,11.7578125,14.40625],"rotation":0,"texture":"#2","tintindex":0},"south":{"uv":[14.3125,11.6875,14.3828125,11.78125],"rotation":0,"texture":"#2","tintindex":0},"north":{"uv":[14.3125,11.5625,14.3828125,11.65625],"rotation":0,"texture":"#2","tintindex":0},"west":{"uv":[11.8125,14.3125,11.8828125,14.40625],"rotation":0,"texture":"#2","tintindex":0},"up":{"uv":[0.6328125,14.6328125,0.5625,14.5625],"rotation":0,"texture":"#2","tintindex":0},"down":{"uv":[14.6328125,0.625,14.5625,0.6953125],"rotation":0,"texture":"#2","tintindex":0}}},{"from":[7.5616074,7.5908356,2.205357],"to":[7.6821427,8.113157,2.6875],"rotation":{"angle":0.0,"axis":"y","origin":[7.6419644,7.8519964,2.4464283]},"faces":{"east":{"uv":[14.75,4.0,14.8046875,4.0585938],"rotation":0,"texture":"#2","tintindex":0},"south":{"uv":[15.1875,7.125,15.199219,7.1835938],"rotation":0,"texture":"#2","tintindex":0},"north":{"uv":[7.125,15.1875,7.1367188,15.246094],"rotation":0,"texture":"#2","tintindex":0},"west":{"uv":[4.0625,14.75,4.1171875,14.808594],"rotation":0,"texture":"#2","tintindex":0},"up":{"uv":[15.199219,13.3671875,15.1875,13.3125],"rotation":0,"texture":"#2","tintindex":0},"down":{"uv":[13.386719,15.1875,13.375,15.2421875],"rotation":0,"texture":"#2","tintindex":0}}},{"from":[7.5616074,8.113157,2.3258924],"to":[7.6821427,8.434586,2.5669641],"rotation":{"angle":0.0,"axis":"y","origin":[7.6419644,8.273871,2.4464283]},"faces":{"east":{"uv":[15.125,2.9375,15.152344,2.9726562],"rotation":0,"texture":"#2","tintindex":0},"south":{"uv":[5.875,15.3125,5.8867188,15.347656],"rotation":0,"texture":"#2","tintindex":0},"north":{"uv":[15.3125,5.8125,15.324219,5.8476562],"rotation":0,"texture":"#2","tintindex":0},"west":{"uv":[3.0,15.125,3.0273438,15.160156],"rotation":0,"texture":"#2","tintindex":0},"up":{"uv":[0.32421875,15.402344,0.3125,15.375],"rotation":0,"texture":"#2","tintindex":0},"down":{"uv":[15.386719,0.3125,15.375,0.33984375],"rotation":0,"texture":"#2","tintindex":0}}},{"from":[8.325,7.5908356,2.2857141],"to":[8.405357,8.113157,2.6071424],"rotation":{"angle":0.0,"axis":"y","origin":[8.365179,7.8519964,2.4464283]},"faces":{"east":{"uv":[14.875,0.25,14.910156,0.30859375],"rotation":0,"texture":"#2","tintindex":0},"south":{"uv":[2.0625,15.3125,2.0703125,15.371094],"rotation":0,"texture":"#2","tintindex":0},"north":{"uv":[15.3125,2.0,15.3203125,2.0585938],"rotation":0,"texture":"#2","tintindex":0},"west":{"uv":[0.3125,14.875,0.34765625,14.933594],"rotation":0,"texture":"#2","tintindex":0},"up":{"uv":[8.5703125,15.410156,8.5625,15.375],"rotation":0,"texture":"#2","tintindex":0},"down":{"uv":[15.3828125,8.5625,15.375,8.597656],"rotation":0,"texture":"#2","tintindex":0}}},{"from":[8.325,8.113157,2.3660712],"to":[8.405357,8.434586,2.5267854],"rotation":{"angle":0.0,"axis":"y","origin":[8.365179,8.273871,2.4464283]},"faces":{"east":{"uv":[7.1875,15.1875,7.2070312,15.222656],"rotation":0,"texture":"#2","tintindex":0},"south":{"uv":[15.375,8.625,15.3828125,8.660156],"rotation":0,"texture":"#2","tintindex":0},"north":{"uv":[8.625,15.375,8.6328125,15.410156],"rotation":0,"texture":"#2","tintindex":0},"west":{"uv":[15.1875,7.1875,15.207031,7.2226562],"rotation":0,"texture":"#2","tintindex":0},"up":{"uv":[15.4453125,13.457031,15.4375,13.4375],"rotation":0,"texture":"#2","tintindex":0},"down":{"uv":[13.5078125,15.4375,13.5,15.457031],"rotation":0,"texture":"#2","tintindex":0}}},{"from":[7.7625,7.5908356,2.0044641],"to":[8.244643,8.113157,2.1249995],"rotation":{"angle":0.0,"axis":"y","origin":[8.0035715,7.9122643,2.3258924]},"faces":{"east":{"uv":[7.25,15.1875,7.2617188,15.246094],"rotation":0,"texture":"#2","tintindex":0},"south":{"uv":[4.125,14.75,4.1796875,14.808594],"rotation":0,"texture":"#2","tintindex":0},"north":{"uv":[14.75,4.0625,14.8046875,4.1210938],"rotation":0,"texture":"#2","tintindex":0},"west":{"uv":[15.1875,7.25,15.199219,7.3085938],"rotation":0,"texture":"#2","tintindex":0},"up":{"uv":[15.2421875,13.386719,15.1875,13.375],"rotation":0,"texture":"#2","tintindex":0},"down":{"uv":[13.4921875,15.1875,13.4375,15.199219],"rotation":0,"texture":"#2","tintindex":0}}},{"from":[7.8870535,8.113157,2.0044641],"to":[8.128125,8.434586,2.1249995],"rotation":{"angle":0.0,"axis":"y","origin":[8.0276785,8.273871,2.064732]},"faces":{"east":{"uv":[15.3125,5.875,15.324219,5.9101562],"rotation":0,"texture":"#2","tintindex":0},"south":{"uv":[3.0625,15.125,3.0898438,15.160156],"rotation":0,"texture":"#2","tintindex":0},"north":{"uv":[15.125,3.0,15.152344,3.0351562],"rotation":0,"texture":"#2","tintindex":0},"west":{"uv":[5.9375,15.3125,5.9492188,15.347656],"rotation":0,"texture":"#2","tintindex":0},"up":{"uv":[0.40234375,15.386719,0.375,15.375],"rotation":0,"texture":"#2","tintindex":0},"down":{"uv":[15.402344,0.375,15.375,0.38671875],"rotation":0,"texture":"#2","tintindex":0}}},{"from":[7.8870535,8.113157,2.767857],"to":[8.128125,8.434586,2.8883924],"rotation":{"angle":0.0,"axis":"y","origin":[8.0276785,8.273871,2.828125]},"faces":{"east":{"uv":[15.3125,5.9375,15.324219,5.9726562],"rotation":0,"texture":"#2","tintindex":0},"south":{"uv":[3.125,15.125,3.1523438,15.160156],"rotation":0,"texture":"#2","tintindex":0},"north":{"uv":[15.125,3.0625,15.152344,3.0976562],"rotation":0,"texture":"#2","tintindex":0},"west":{"uv":[6.0,15.3125,6.0117188,15.347656],"rotation":0,"texture":"#2","tintindex":0},"up":{"uv":[0.46484375,15.386719,0.4375,15.375],"rotation":0,"texture":"#2","tintindex":0},"down":{"uv":[15.402344,0.4375,15.375,0.44921875],"rotation":0,"texture":"#2","tintindex":0}}},{"from":[7.7625,7.5908356,2.767857],"to":[8.244643,8.113157,2.8883924],"rotation":{"angle":0.0,"axis":"y","origin":[8.0035715,7.9122643,3.0892854]},"faces":{"east":{"uv":[7.3125,15.1875,7.3242188,15.246094],"rotation":0,"texture":"#2","tintindex":0},"south":{"uv":[4.1875,14.75,4.2421875,14.808594],"rotation":0,"texture":"#2","tintindex":0},"north":{"uv":[14.75,4.125,14.8046875,4.1835938],"rotation":0,"texture":"#2","tintindex":0},"west":{"uv":[15.1875,7.3125,15.199219,7.3710938],"rotation":0,"texture":"#2","tintindex":0},"up":{"uv":[15.2421875,13.449219,15.1875,13.4375],"rotation":0,"texture":"#2","tintindex":0},"down":{"uv":[13.5546875,15.1875,13.5,15.199219],"rotation":0,"texture":"#2","tintindex":0}}}],"display":{"head":{"translation":[0.0,-6.4,0.0],"scale":[4.0,4.0,4.0]}}}