{"textures":{"3":"modelengine:entity/foreleftleg"},"elements":[{"from":[6.9094253,-1.3761597,7.528264],"to":[7.9094253,-0.62615967,10.028264],"faces":{"east":{"uv":[7.5,4.0,9.0,4.5],"tintindex":0,"rotation":0,"texture":"#3"},"south":{"uv":[7.0,7.5,7.5,8.0],"tintindex":0,"rotation":0,"texture":"#3"},"north":{"uv":[6.0,5.5,6.5,6.0],"tintindex":0,"rotation":0,"texture":"#3"},"west":{"uv":[7.5,4.5,9.0,5.0],"tintindex":0,"rotation":0,"texture":"#3"},"up":{"uv":[4.5,8.0,4.0,6.5],"tintindex":0,"rotation":0,"texture":"#3"},"down":{"uv":[1.5,7.0,1.0,8.5],"tintindex":0,"rotation":0,"texture":"#3"}}}]}