{"textures":{"4":"modelengine:entity/head_redeyes"},"elements":[{"from":[8.340099,8.391273,6.789112],"to":[9.6258135,10.391273,7.503398],"rotation":{"angle":0.0,"axis":"y","origin":[8.268671,9.676987,7.860541]},"faces":{"east":{"uv":[4.375,2.25,4.5,2.75],"rotation":0,"texture":"#4","tintindex":0},"south":{"uv":[0.5,7.375,0.75,7.875],"rotation":0,"texture":"#4","tintindex":0},"north":{"uv":[0.25,7.375,0.5,7.875],"rotation":0,"texture":"#4","tintindex":0},"west":{"uv":[1.125,5.25,1.25,5.75],"rotation":0,"texture":"#4","tintindex":0},"up":{"uv":[4.875,7.625,4.625,7.5],"rotation":0,"texture":"#4","tintindex":0},"down":{"uv":[7.75,5.25,7.5,5.375],"rotation":0,"texture":"#4","tintindex":0}}}],"display":{"head":{"translation":[0.0,-6.4,0.0],"scale":[4.0,4.0,4.0]}}}