{"textures":{"0":"modelengine:entity/crate"},"elements":[{"from":[-11.5,7.9000015,25.8],"to":[28.5,11.900002,27.8],"faces":{"east":{"uv":[3.75,7.0,3.875,7.25],"tintindex":0,"rotation":0,"texture":"#0"},"south":{"uv":[4.0,2.0,6.5,2.25],"tintindex":0,"rotation":0,"texture":"#0"},"north":{"uv":[2.0,4.0,4.5,4.25],"tintindex":0,"rotation":0,"texture":"#0"},"west":{"uv":[3.875,7.0,4.0,7.25],"tintindex":0,"rotation":0,"texture":"#0"},"up":{"uv":[9.0,2.125,6.5,2.0],"tintindex":0,"rotation":0,"texture":"#0"},"down":{"uv":[9.0,2.125,6.5,2.25],"tintindex":0,"rotation":0,"texture":"#0"}}}]}